dsrf_finder/__init__.py
dsrf_finder/dsrf_finder.py
dsrf_finder-0.0.4.post5.dist-info/LICENSE
dsrf_finder-0.0.4.post5.dist-info/METADATA
dsrf_finder-0.0.4.post5.dist-info/WHEEL
dsrf_finder-0.0.4.post5.dist-info/top_level.txt
dsrf_finder-0.0.4.post5.dist-info/RECORD
