Metadata-Version: 2.1
Name: dsrf-finder
Version: 0.0.4-5
Summary: This library intends to make parsing HTML (e.g. scraping the web) as simple, intuitive and make the scrape as fast as possible.
Home-page: https://github.com/thedsrf/dsrf_finder
Author: Anas bin hasan bhuiyan
Author-email: dsrf.anas@gmail.com
License: UNKNOWN
Project-URL: Bug Tracker, https://github.com/thedsrf/dsrf_finder/issues
Platform: UNKNOWN
Classifier: Programming Language :: Python :: 3
Classifier: License :: OSI Approved :: MIT License
Classifier: Operating System :: OS Independent
Requires-Python: >=3.6
License-File: LICENSE
Requires-Dist: requests
Requires-Dist: requests-html
Requires-Dist: jsonpath-ng
